fallback_view/__init__.py
fallback_view/middleware.py
fallback_view/settings.py
fallback_view/utils.py
tests/integration/__init__.py
tests/unit/__init__.py
django_fallback_view-0.2.0.dist-info/LICENSE.txt
django_fallback_view-0.2.0.dist-info/METADATA
django_fallback_view-0.2.0.dist-info/WHEEL
django_fallback_view-0.2.0.dist-info/top_level.txt
django_fallback_view-0.2.0.dist-info/RECORD
